ais140/__init__.py
ais140/kpi.py
ais140/parser.py
tests/__init__.py
tests/test_parser.py
ais140_parser-1.0.0.dist-info/METADATA
ais140_parser-1.0.0.dist-info/WHEEL
ais140_parser-1.0.0.dist-info/top_level.txt
ais140_parser-1.0.0.dist-info/RECORD
