Metadata-Version: 2.4
Name: ais140-parser
Version: 1.0.0
Summary: AIS140 Protocol Parser
Home-page: https://github.com/knarsing/ais140-parser
Author: knarsing
Author-email: narsing.pimple@gmail.com
License: MIT
Classifier: Programming Language :: Python :: 3
Classifier: License :: OSI Approved :: MIT License
Classifier: Operating System :: OS Independent
Requires-Python: >=3.6
Dynamic: author
Dynamic: author-email
Dynamic: classifier
Dynamic: description
Dynamic: description-content-type
Dynamic: home-page
Dynamic: license
Dynamic: requires-python
Dynamic: summary
